setup.py
cachedgenerator/__init__.py
cachedgenerator/implementation.py
cachedgenerator.egg-info/PKG-INFO
cachedgenerator.egg-info/SOURCES.txt
cachedgenerator.egg-info/dependency_links.txt
cachedgenerator.egg-info/not-zip-safe
cachedgenerator.egg-info/top_level.txt