Metadata-Version: 1.1
Name: cachedgenerator
Version: 0.1.0
Summary: Caching generators has never been prettier.
Home-page: https://github.com/rinslow/cachedgenerator
Author: Dan Elkis
Author-email: elkissdan@gmail.com
License: MIT
Keywords: cached,cache,caching,generator,generators,cachedgenerator,cached_generator
Platform: UNKNOWN
Classifier: License :: OSI Approved :: MIT License
Classifier: Operating System :: OS Independent
Classifier: Programming Language :: Python
Classifier: Programming Language :: Python :: 2
Classifier: Programming Language :: Python :: 2.7
Classifier: Programming Language :: Python :: 3
Classifier: Programming Language :: Python :: 3.4
Classifier: Programming Language :: Python :: 3.5
Classifier: Programming Language :: Python :: 3.6
Classifier: Programming Language :: Python :: Implementation :: CPython
Classifier: Programming Language :: Python :: Implementation :: PyPy
